py_financas/LICENSE.txt
py_financas/__init__.py
py_financas/constantes.py
py_financas/_utils/__init__.py
py_financas/_utils/arquivos_zip.py
py_financas/_utils/autenticacao.py
py_financas/_utils/unidades_brasileiras.py
py_financas/bcb_sgs/__init__.py
py_financas/bcb_sgs/recupera_indice.py
py_financas/bcb_sgs/tabela_de_codigos_sistemas_web_banco_central_do_brasil.csv
py_financas/cvm/__init__.py
py_financas/cvm/recupera_cadastros_fundos.py
py_financas/cvm/recupera_informes_diarios_de_hoje.py
py_financas/sinacor/__init__.py
py_financas/sinacor/parser.py
py_financas/sinacor/positions.py
py_financas/sinacor/types.py
py_financas-1.0.2.dist-info/METADATA
py_financas-1.0.2.dist-info/WHEEL
py_financas-1.0.2.dist-info/licenses/LICENSE
py_financas-1.0.2.dist-info/RECORD
