Metadata-Version: 2.3
Name: py_financas
Version: 1.0.2
Summary: Py Finanças é um pacote python que simplifica obtenção e uso de dados do sistema financeiro brasileiro.
Project-URL: Homepage, https://github.com/jfrfonseca/py_financas
Project-URL: Documentation, https://github.com/jfrfonseca/py_financas/README.md
Project-URL: Issues, https://github.com/jfrfonseca/py_financas/issues
Author-email: José Fonseca <jfra.fonseca@gmail.com>
License-File: LICENSE
Classifier: License :: Other/Proprietary License
Classifier: Operating System :: OS Independent
Classifier: Programming Language :: Python :: 3
Requires-Python: >=3.6.0
Requires-Dist: numpy
Requires-Dist: openpyxl
Requires-Dist: pandas
Requires-Dist: pdfplumber
Requires-Dist: pydantic
Requires-Dist: requests
Requires-Dist: suds
Requires-Dist: unidecode
Requires-Dist: xmltodict
